README.md
setup.py
vblocks/__init__.py
vblocks/block.py
vblocks/component.py
vblocks/composition.py
vblocks/element.py
vblocks/enums.py
vblocks/view.py
vblocks.egg-info/PKG-INFO
vblocks.egg-info/SOURCES.txt
vblocks.egg-info/dependency_links.txt
vblocks.egg-info/top_level.txt