Metadata-Version: 2.1
Name: vblocks
Version: 0.0.1
Summary: UNKNOWN
Home-page: UNKNOWN
Author: Spencer Neveux
License: UNKNOWN
Platform: UNKNOWN
